ndclient/__init__.py
ndclient/client.py
tests/__init__.py
tests/test_api.py
ndclient-0.1.3.dist-info/LICENSE
ndclient-0.1.3.dist-info/METADATA
ndclient-0.1.3.dist-info/WHEEL
ndclient-0.1.3.dist-info/top_level.txt
ndclient-0.1.3.dist-info/RECORD
